{
  "users": [
    {
      "id": "6304f98b42ade0e7e65c2aee",
      "index": 0,
      "guid": "75c95815-9c6d-4f0d-8d2c-a3308d577179",
      "isActive": false,
      "balance": "$2,359.78",
      "picture": "http://placehold.it/32x32",
      "age": 29,
      "eyeColor": "green",
      "name": "Daphne Rivera",
      "gender": "female",
      "company": "JIMBIES",
      "email": "daphnerivera@jimbies.com",
      "phone": "+1 (826) 587-3300",
      "address": "381 Provost Street, Woodburn, Ohio, 1809",
      "about": "Minim deserunt ad dolore deserunt exercitation amet reprehenderit in ea ut. Velit incididunt aute in reprehenderit. Pariatur id et ut consectetur qui sint amet excepteur quis labore enim laborum dolor eu. Mollit dolor proident dolore adipisicing reprehenderit ipsum non duis enim aliquip ea do pariatur et.\r\n",
      "registered": "2016-06-11T07:52:32 -02:00",
      "latitude": 52.822864,
      "longitude": -116.896735,
      "tags": [
        "ipsum",
        "tempor",
        "amet",
        "pariatur",
        "sunt",
        "ad",
        "id"
      ],
      "friends": [
        {
          "id": 0,
          "name": "Sellers Nolan"
        },
        {
          "id": 1,
          "name": "Charity Mckenzie"
        },
        {
          "id": 2,
          "name": "Anna Marshall"
        }
      ],
      "greeting": "Hello, Daphne Rivera! You have 1 unread messages.",
      "favoriteFruit": "strawberry"
    },
    {
      "id": "6304f98ba6c97d46b2d3bfe9",
      "index": 1,
      "guid": "7b218a1b-c5e1-4f12-b26b-6690692e0164",
      "isActive": false,
      "balance": "$1,419.00",
      "picture": "http://placehold.it/32x32",
      "age": 22,
      "eyeColor": "green",
      "name": "Britt Francis",
      "gender": "male",
      "company": "SNACKTION",
      "email": "brittfrancis@snacktion.com",
      "phone": "+1 (882) 502-2030",
      "address": "879 Wyckoff Street, Elizaville, Wyoming, 593",
      "about": "Voluptate dolor in est occaecat adipisicing est occaecat cupidatat laboris esse id. Occaecat cillum sit officia velit ad Lorem Lorem magna. Excepteur elit sit laborum ad. Quis mollit non dolore excepteur anim et occaecat. Reprehenderit amet eu labore dolore aliquip consequat nostrud elit aute duis minim. Qui ex veniam incididunt veniam aute id mollit anim ut nisi magna.\r\n",
      "registered": "2020-03-07T03:20:17 -01:00",
      "latitude": 75.636578,
      "longitude": 170.132288,
      "tags": [
        "fugiat",
        "qui",
        "consequat",
        "nostrud",
        "excepteur",
        "irure",
        "qui"
      ],
      "friends": [
        {
          "id": 0,
          "name": "Santana Velasquez"
        },
        {
          "id": 1,
          "name": "Flossie Cain"
        },
        {
          "id": 2,
          "name": "Riley Crosby"
        }
      ],
      "greeting": "Hello, Britt Francis! You have 10 unread messages.",
      "favoriteFruit": "banana"
    },
    {
      "id": "6304f98b3001c6c324a9aec9",
      "index": 2,
      "guid": "c547bf10-e0c9-442f-9faa-b5c214031f9d",
      "isActive": false,
      "balance": "$2,780.07",
      "picture": "http://placehold.it/32x32",
      "age": 30,
      "eyeColor": "brown",
      "name": "Mcfadden Riley",
      "gender": "male",
      "company": "TERRASYS",
      "email": "mcfaddenriley@terrasys.com",
      "phone": "+1 (955) 511-2808",
      "address": "895 Elmwood Avenue, Grazierville, Arizona, 667",
      "about": "Ad culpa culpa fugiat enim labore fugiat. Ullamco voluptate Lorem consectetur non incididunt ut ipsum commodo deserunt. Minim do ullamco consectetur exercitation magna occaecat adipisicing fugiat ad ex est quis irure dolor. In aliqua Lorem culpa culpa voluptate cupidatat anim fugiat. Proident cupidatat eiusmod dolor consequat nostrud veniam irure aliqua incididunt sunt amet commodo officia.\r\n",
      "registered": "2015-11-18T08:02:18 -01:00",
      "latitude": 24.991092,
      "longitude": 72.877814,
      "tags": [
        "nostrud",
        "dolor",
        "duis",
        "non",
        "officia",
        "mollit",
        "enim"
      ],
      "friends": [
        {
          "id": 0,
          "name": "Tamika Burgess"
        },
        {
          "id": 1,
          "name": "Becky Meyer"
        },
        {
          "id": 2,
          "name": "Daniels Beasley"
        }
      ],
      "greeting": "Hello, Mcfadden Riley! You have 7 unread messages.",
      "favoriteFruit": "strawberry"
    },
    {
      "id": "6304f98bef71a6d06f7e3bf5",
      "index": 3,
      "guid": "e61955bb-2c98-4e43-8893-822c692f8411",
      "isActive": false,
      "balance": "$1,940.83",
      "picture": "http://placehold.it/32x32",
      "age": 24,
      "eyeColor": "brown",
      "name": "Tina Higgins",
      "gender": "female",
      "company": "EVEREST",
      "email": "tinahiggins@everest.com",
      "phone": "+1 (920) 529-3652",
      "address": "690 Church Lane, Roberts, Guam, 9306",
      "about": "Ipsum non proident fugiat occaecat reprehenderit consequat eiusmod ad laboris nostrud occaecat. Do do Lorem nulla laboris aute labore non. Pariatur amet et nulla enim sit consequat velit ad reprehenderit.\r\n",
      "registered": "2015-01-04T10:23:09 -01:00",
      "latitude": 64.203545,
      "longitude": -95.193917,
      "tags": [
        "mollit",
        "aliqua",
        "do",
        "tempor",
        "labore",
        "est",
        "proident"
      ],
      "friends": [
        {
          "id": 0,
          "name": "Sweet Cote"
        },
        {
          "id": 1,
          "name": "Gail Hubbard"
        },
        {
          "id": 2,
          "name": "Davenport Wiley"
        }
      ],
      "greeting": "Hello, Tina Higgins! You have 1 unread messages.",
      "favoriteFruit": "strawberry"
    },
    {
      "id": "6304f98b4daa3b793697b823",
      "index": 4,
      "guid": "1711369a-a057-406f-bdfa-5ec484cfec0e",
      "isActive": true,
      "balance": "$2,582.64",
      "picture": "http://placehold.it/32x32",
      "age": 31,
      "eyeColor": "brown",
      "name": "Leta Klein",
      "gender": "female",
      "company": "GINKOGENE",
      "email": "letaklein@ginkogene.com",
      "phone": "+1 (883) 560-3851",
      "address": "258 Vanderbilt Avenue, Linwood, West Virginia, 4376",
      "about": "Est non culpa aliquip incididunt aute excepteur enim ut occaecat officia laborum ad. Dolore et voluptate magna id magna enim laborum aliqua. Aute sunt ut sunt deserunt eu aute nostrud do fugiat. Enim deserunt ad et sit. Enim laborum commodo anim quis minim. Ex culpa officia nulla id consectetur fugiat ex ea nulla. Ad consectetur reprehenderit nostrud excepteur culpa.\r\n",
      "registered": "2018-02-21T10:08:20 -01:00",
      "latitude": -36.497441,
      "longitude": -157.243061,
      "tags": [
        "reprehenderit",
        "nostrud",
        "sit",
        "ut",
        "minim",
        "ullamco",
        "irure"
      ],
      "friends": [
        {
          "id": 0,
          "name": "Stafford Bennett"
        },
        {
          "id": 1,
          "name": "Juliette Mclaughlin"
        },
        {
          "id": 2,
          "name": "Larson Conway"
        }
      ],
      "greeting": "Hello, Leta Klein! You have 3 unread messages.",
      "favoriteFruit": "strawberry"
    },
    {
      "id": "6304f98b3ce973e12a9f33fb",
      "index": 5,
      "guid": "b3bb92c9-dfb2-45a7-8ba8-f3c1ca558fc2",
      "isActive": false,
      "balance": "$3,205.97",
      "picture": "http://placehold.it/32x32",
      "age": 29,
      "eyeColor": "blue",
      "name": "Burnett Randall",
      "gender": "male",
      "company": "TELPOD",
      "email": "burnettrandall@telpod.com",
      "phone": "+1 (871) 597-3031",
      "address": "204 Applegate Court, Devon, Nebraska, 6579",
      "about": "Sunt ex aute reprehenderit pariatur deserunt aute ea incididunt. Aliquip Lorem sunt duis tempor. Nostrud anim laborum pariatur commodo voluptate.\r\n",
      "registered": "2015-04-12T10:00:43 -02:00",
      "latitude": -19.273867,
      "longitude": -121.049192,
      "tags": [
        "quis",
        "dolore",
        "id",
        "exercitation",
        "officia",
        "ut",
        "deserunt"
      ],
      "friends": [
        {
          "id": 0,
          "name": "Ferguson Silva"
        },
        {
          "id": 1,
          "name": "Nikki Delacruz"
        },
        {
          "id": 2,
          "name": "Craft Hinton"
        }
      ],
      "greeting": "Hello, Burnett Randall! You have 6 unread messages.",
      "favoriteFruit": "strawberry"
    },
    {
      "id": "6304f98ba85354376e50b284",
      "index": 6,
      "guid": "2a3b98c9-4a3c-4294-a574-174acdc34428",
      "isActive": false,
      "balance": "$3,368.26",
      "picture": "http://placehold.it/32x32",
      "age": 30,
      "eyeColor": "brown",
      "name": "Patrica Maynard",
      "gender": "female",
      "company": "NEXGENE",
      "email": "patricamaynard@nexgene.com",
      "phone": "+1 (914) 547-2853",
      "address": "210 Schermerhorn Street, Grill, New Mexico, 881",
      "about": "Elit ipsum eiusmod amet sunt consectetur exercitation consectetur. Labore do consectetur elit culpa. Sunt elit nisi irure nulla pariatur proident duis fugiat. Sit irure qui ullamco mollit mollit enim non consectetur velit nulla tempor. Nulla nisi do excepteur dolore labore id Lorem ex. Eu aute proident deserunt commodo excepteur enim anim velit aliquip exercitation consectetur excepteur. Nostrud ipsum deserunt pariatur esse dolore dolor esse ipsum amet consequat exercitation incididunt.\r\n",
      "registered": "2021-07-26T10:07:28 -02:00",
      "latitude": -19.957524,
      "longitude": 85.155469,
      "tags": [
        "laboris",
        "reprehenderit",
        "esse",
        "minim",
        "fugiat",
        "laborum",
        "labore"
      ],
      "friends": [
        {
          "id": 0,
          "name": "Minnie Armstrong"
        },
        {
          "id": 1,
          "name": "Velasquez Nicholson"
        },
        {
          "id": 2,
          "name": "Glenn Santos"
        }
      ],
      "greeting": "Hello, Patrica Maynard! You have 10 unread messages.",
      "favoriteFruit": "apple"
    },
    {
      "id": "6304f98b3095f1a18c04939e",
      "index": 7,
      "guid": "21d7dc2a-ca22-449d-b925-de35030a0eb3",
      "isActive": false,
      "balance": "$2,316.60",
      "picture": "http://placehold.it/32x32",
      "age": 39,
      "eyeColor": "blue",
      "name": "Callie Coleman",
      "gender": "female",
      "company": "WARETEL",
      "email": "calliecoleman@waretel.com",
      "phone": "+1 (990) 585-2111",
      "address": "418 Beaver Street, Woodlake, Washington, 3241",
      "about": "Ea ea enim nulla id fugiat non Lorem Lorem. Quis voluptate culpa esse anim qui sint sit dolor ea. Anim in commodo non magna proident. Nostrud tempor pariatur excepteur duis deserunt laboris culpa dolore ut sint. Amet proident esse elit officia magna veniam minim sint et sunt.\r\n",
      "registered": "2021-06-24T05:13:17 -02:00",
      "latitude": 23.601864,
      "longitude": 27.150132,
      "tags": [
        "velit",
        "eu",
        "sit",
        "do",
        "nisi",
        "anim",
        "Lorem"
      ],
      "friends": [
        {
          "id": 0,
          "name": "Blanca Salinas"
        },
        {
          "id": 1,
          "name": "West Clements"
        },
        {
          "id": 2,
          "name": "Cooke Simon"
        }
      ],
      "greeting": "Hello, Callie Coleman! You have 4 unread messages.",
      "favoriteFruit": "apple"
    },
    {
      "id": "6304f98b83add100f072e235",
      "index": 8,
      "guid": "fcbd5beb-dc73-4a68-aa3e-1ae1a126d2e9",
      "isActive": false,
      "balance": "$3,789.27",
      "picture": "http://placehold.it/32x32",
      "age": 23,
      "eyeColor": "blue",
      "name": "Reyna Conley",
      "gender": "female",
      "company": "DECRATEX",
      "email": "reynaconley@decratex.com",
      "phone": "+1 (822) 500-2110",
      "address": "548 Vernon Avenue, Elrama, Nevada, 8847",
      "about": "Occaecat sint commodo occaecat aliqua labore aliqua est sunt. Lorem irure deserunt dolore id dolor excepteur minim aliqua exercitation in cillum esse duis sint. Ullamco et nisi nulla velit est consequat dolor occaecat enim non tempor laboris. Velit aute labore commodo irure duis esse eiusmod sit dolore in laborum elit culpa.\r\n",
      "registered": "2015-05-13T01:33:39 -02:00",
      "latitude": -81.967621,
      "longitude": -80.481875,
      "tags": [
        "laboris",
        "eiusmod",
        "dolor",
        "non",
        "ut",
        "ipsum",
        "anim"
      ],
      "friends": [
        {
          "id": 0,
          "name": "Ayala Jordan"
        },
        {
          "id": 1,
          "name": "Molina Pollard"
        },
        {
          "id": 2,
          "name": "Clark Curtis"
        }
      ],
      "greeting": "Hello, Reyna Conley! You have 4 unread messages.",
      "favoriteFruit": "apple"
    },
    {
      "id": "6304f98bef46e618b58be37b",
      "index": 9,
      "guid": "dc97052a-f9b8-4f3b-b454-94c5cd8c084c",
      "isActive": true,
      "balance": "$1,533.64",
      "picture": "http://placehold.it/32x32",
      "age": 32,
      "eyeColor": "green",
      "name": "Parsons Santana",
      "gender": "male",
      "company": "PEARLESEX",
      "email": "parsonssantana@pearlesex.com",
      "phone": "+1 (968) 593-2017",
      "address": "747 Nixon Court, Sardis, Marshall Islands, 1893",
      "about": "Duis incididunt irure duis magna ullamco anim Lorem amet aute incididunt officia. Amet elit reprehenderit in ipsum culpa. Dolore reprehenderit reprehenderit tempor esse ad enim aliqua laborum ut. Esse duis sit sit enim ad est exercitation nostrud consectetur sunt. Elit fugiat ad id ex excepteur.\r\n",
      "registered": "2017-03-25T03:33:24 -01:00",
      "latitude": -7.30485,
      "longitude": 38.392998,
      "tags": [
        "nulla",
        "dolor",
        "id",
        "elit",
        "ipsum",
        "fugiat",
        "dolor"
      ],
      "friends": [
        {
          "id": 0,
          "name": "Francis Bush"
        },
        {
          "id": 1,
          "name": "Letha Wilkerson"
        },
        {
          "id": 2,
          "name": "Morrow Estrada"
        }
      ],
      "greeting": "Hello, Parsons Santana! You have 2 unread messages.",
      "favoriteFruit": "banana"
    },
    {
      "id": "6304f98b1e60cfe675aa10a5",
      "index": 10,
      "guid": "e7189d65-e193-4901-854a-ea4d9d127d72",
      "isActive": true,
      "balance": "$1,465.73",
      "picture": "http://placehold.it/32x32",
      "age": 29,
      "eyeColor": "green",
      "name": "Mari Vincent",
      "gender": "female",
      "company": "DADABASE",
      "email": "marivincent@dadabase.com",
      "phone": "+1 (924) 501-3354",
      "address": "690 Hall Street, Norvelt, Louisiana, 7941",
      "about": "Irure eu reprehenderit enim eu sunt. Esse esse velit fugiat mollit. Laborum qui proident nulla laboris eu. Fugiat cillum cupidatat esse ea exercitation. Dolor irure duis esse proident aliquip dolore. Aliquip quis non sit sint occaecat reprehenderit deserunt deserunt eu non. Duis incididunt sint amet sit laborum non.\r\n",
      "registered": "2021-02-22T09:30:27 -01:00",
      "latitude": -74.662648,
      "longitude": -179.787451,
      "tags": [
        "occaecat",
        "excepteur",
        "laboris",
        "nulla",
        "et",
        "aliquip",
        "labore"
      ],
      "friends": [
        {
          "id": 0,
          "name": "Iris Shannon"
        },
        {
          "id": 1,
          "name": "Valeria Shepard"
        },
        {
          "id": 2,
          "name": "Terry Hess"
        }
      ],
      "greeting": "Hello, Mari Vincent! You have 6 unread messages.",
      "favoriteFruit": "apple"
    },
    {
      "id": "6304f98bd6bd9d9374352805",
      "index": 11,
      "guid": "7327f9ca-fb46-4118-a1db-61883db545ba",
      "isActive": false,
      "balance": "$2,342.31",
      "picture": "http://placehold.it/32x32",
      "age": 23,
      "eyeColor": "green",
      "name": "Kate Vasquez",
      "gender": "female",
      "company": "SCHOOLIO",
      "email": "katevasquez@schoolio.com",
      "phone": "+1 (812) 589-3187",
      "address": "221 Fillmore Avenue, Adamstown, Missouri, 9533",
      "about": "Laboris cupidatat enim aliqua quis irure elit ad. Deserunt qui tempor dolor adipisicing anim non cupidatat aute et. Occaecat quis officia magna do reprehenderit aute occaecat ipsum anim sint velit qui velit.\r\n",
      "registered": "2019-10-23T06:08:42 -02:00",
      "latitude": -65.421193,
      "longitude": -124.562274,
      "tags": [
        "anim",
        "deserunt",
        "adipisicing",
        "consectetur",
        "commodo",
        "tempor",
        "amet"
      ],
      "friends": [
        {
          "id": 0,
          "name": "Juliet Dunlap"
        },
        {
          "id": 1,
          "name": "Esperanza Hodge"
        },
        {
          "id": 2,
          "name": "Nora Hensley"
        }
      ],
      "greeting": "Hello, Kate Vasquez! You have 10 unread messages.",
      "favoriteFruit": "strawberry"
    },
    {
      "id": "6304f98be35b259877d58f5c",
      "index": 12,
      "guid": "3a104242-0926-422d-b210-2aaa63896167",
      "isActive": false,
      "balance": "$1,013.63",
      "picture": "http://placehold.it/32x32",
      "age": 33,
      "eyeColor": "blue",
      "name": "Effie Shaw",
      "gender": "female",
      "company": "QUORDATE",
      "email": "effieshaw@quordate.com",
      "phone": "+1 (805) 557-2810",
      "address": "716 Thornton Street, Dragoon, Minnesota, 914",
      "about": "Adipisicing excepteur laboris aliqua fugiat anim pariatur. Dolor do eu cillum exercitation non fugiat pariatur enim anim qui sit. Cillum occaecat nulla culpa elit exercitation irure Lorem excepteur non. In occaecat commodo veniam ipsum est consectetur aute dolore sunt cupidatat est labore dolore proident.\r\n",
      "registered": "2014-09-14T08:51:55 -02:00",
      "latitude": 2.264543,
      "longitude": 171.547456,
      "tags": [
        "incididunt",
        "exercitation",
        "ut",
        "Lorem",
        "commodo",
        "pariatur",
        "consequat"
      ],
      "friends": [
        {
          "id": 0,
          "name": "Dominguez Ramsey"
        },
        {
          "id": 1,
          "name": "Walter Crane"
        },
        {
          "id": 2,
          "name": "Reyes Webb"
        }
      ],
      "greeting": "Hello, Effie Shaw! You have 7 unread messages.",
      "favoriteFruit": "banana"
    },
    {
      "id": "6304f98b76cc36cc11bacbc8",
      "index": 13,
      "guid": "069792e9-3326-4a3c-99c8-3e002287f892",
      "isActive": true,
      "balance": "$3,193.39",
      "picture": "http://placehold.it/32x32",
      "age": 29,
      "eyeColor": "green",
      "name": "Cherie Guerra",
      "gender": "female",
      "company": "FUTURIS",
      "email": "cherieguerra@futuris.com",
      "phone": "+1 (828) 461-2625",
      "address": "377 Tapscott Avenue, Hickory, Florida, 3498",
      "about": "Nostrud aute aute commodo fugiat consequat adipisicing id aliquip eu magna adipisicing nulla ex minim. Sunt adipisicing ipsum incididunt labore laborum excepteur officia quis irure enim exercitation. Aliquip proident amet pariatur laboris do. Consequat laboris nostrud qui aliqua ut dolor eiusmod deserunt sunt.\r\n",
      "registered": "2015-03-23T04:50:26 -01:00",
      "latitude": 82.269149,
      "longitude": 125.982157,
      "tags": [
        "incididunt",
        "eu",
        "tempor",
        "eu",
        "reprehenderit",
        "sit",
        "laboris"
      ],
      "friends": [
        {
          "id": 0,
          "name": "Marianne Golden"
        },
        {
          "id": 1,
          "name": "Whitaker Clark"
        },
        {
          "id": 2,
          "name": "Kerry Potter"
        }
      ],
      "greeting": "Hello, Cherie Guerra! You have 8 unread messages.",
      "favoriteFruit": "strawberry"
    },
    {
      "id": "6304f98b4434e6e769733a57",
      "index": 14,
      "guid": "4d3b7628-626f-4b82-8b57-ebeadb302eca",
      "isActive": true,
      "balance": "$3,346.98",
      "picture": "http://placehold.it/32x32",
      "age": 35,
      "eyeColor": "blue",
      "name": "Larsen Daugherty",
      "gender": "male",
      "company": "DOGTOWN",
      "email": "larsendaugherty@dogtown.com",
      "phone": "+1 (811) 490-2318",
      "address": "685 Friel Place, Moscow, New Hampshire, 8902",
      "about": "Ex officia occaecat reprehenderit cupidatat ad nostrud velit aute ea adipisicing. Amet laboris est sint dolor pariatur deserunt. Consectetur quis amet occaecat ea culpa minim aliquip.\r\n",
      "registered": "2018-05-29T02:50:22 -02:00",
      "latitude": -85.606746,
      "longitude": 80.121627,
      "tags": [
        "culpa",
        "enim",
        "velit",
        "non",
        "irure",
        "deserunt",
        "est"
      ],
      "friends": [
        {
          "id": 0,
          "name": "Ferrell Madden"
        },
        {
          "id": 1,
          "name": "Hayes Franks"
        },
        {
          "id": 2,
          "name": "Durham Gay"
        }
      ],
      "greeting": "Hello, Larsen Daugherty! You have 8 unread messages.",
      "favoriteFruit": "strawberry"
    },
    {
      "id": "6304f98be2f426d659a6c171",
      "index": 15,
      "guid": "aeb87038-2e32-4122-a073-bf0d97fc9571",
      "isActive": true,
      "balance": "$3,427.97",
      "picture": "http://placehold.it/32x32",
      "age": 32,
      "eyeColor": "green",
      "name": "Luella Black",
      "gender": "female",
      "company": "ZENTILITY",
      "email": "luellablack@zentility.com",
      "phone": "+1 (864) 491-3398",
      "address": "608 Nolans Lane, Soham, Kentucky, 837",
      "about": "Incididunt amet nulla reprehenderit aute. Dolore laboris quis et cillum adipisicing non exercitation duis velit aliqua qui enim in aliquip. Do ea et cupidatat minim pariatur cillum tempor mollit nisi nisi. Consectetur officia fugiat deserunt dolore officia aliqua et aliqua id dolore exercitation tempor excepteur. Deserunt dolor amet nostrud velit ut adipisicing culpa do tempor duis in excepteur. Sint ex nostrud aliqua occaecat aliqua ea ut cupidatat Lorem consectetur esse id officia ullamco.\r\n",
      "registered": "2017-06-07T06:21:51 -02:00",
      "latitude": -40.912233,
      "longitude": 9.481229,
      "tags": [
        "irure",
        "esse",
        "eu",
        "ad",
        "culpa",
        "ipsum",
        "aute"
      ],
      "friends": [
        {
          "id": 0,
          "name": "Alice Barrera"
        },
        {
          "id": 1,
          "name": "Marquita Bender"
        },
        {
          "id": 2,
          "name": "Glover Berger"
        }
      ],
      "greeting": "Hello, Luella Black! You have 10 unread messages.",
      "favoriteFruit": "strawberry"
    },
    {
      "id": "6304f98b6d6b42556fb07831",
      "index": 16,
      "guid": "786cc6f5-85b1-4044-b1d9-5883ba001189",
      "isActive": true,
      "balance": "$3,897.08",
      "picture": "http://placehold.it/32x32",
      "age": 30,
      "eyeColor": "brown",
      "name": "Joni Solis",
      "gender": "female",
      "company": "FIBRODYNE",
      "email": "jonisolis@fibrodyne.com",
      "phone": "+1 (930) 552-3749",
      "address": "586 Monroe Place, Coloma, Texas, 7012",
      "about": "Pariatur ut veniam duis qui et aute dolor consectetur minim consequat. Esse amet in aliqua ex aliqua. Ullamco laboris sint laboris tempor eiusmod minim labore nostrud quis anim velit aliqua veniam. Et minim consectetur aliquip occaecat ut mollit nostrud fugiat magna aliqua sunt. Tempor consectetur enim tempor eu minim laborum incididunt nulla.\r\n",
      "registered": "2021-02-23T06:33:32 -01:00",
      "latitude": 79.823348,
      "longitude": 64.576244,
      "tags": [
        "deserunt",
        "est",
        "consequat",
        "ipsum",
        "est",
        "ullamco",
        "esse"
      ],
      "friends": [
        {
          "id": 0,
          "name": "Gwendolyn Roach"
        },
        {
          "id": 1,
          "name": "Tiffany Hanson"
        },
        {
          "id": 2,
          "name": "Kelli Meyers"
        }
      ],
      "greeting": "Hello, Joni Solis! You have 8 unread messages.",
      "favoriteFruit": "banana"
    },
    {
      "id": "6304f98b84a27441a1fcfbbb",
      "index": 17,
      "guid": "207df83c-476c-4c36-8a54-31a0f2ade0e8",
      "isActive": false,
      "balance": "$2,001.02",
      "picture": "http://placehold.it/32x32",
      "age": 23,
      "eyeColor": "blue",
      "name": "Jenna Jacobson",
      "gender": "female",
      "company": "BEZAL",
      "email": "jennajacobson@bezal.com",
      "phone": "+1 (902) 591-2454",
      "address": "947 Locust Street, Dante, Palau, 2631",
      "about": "Sunt nisi excepteur officia amet ex non eiusmod amet minim. Ex commodo non anim eu aliqua magna aliquip minim cupidatat commodo incididunt elit labore consequat. Ut qui cupidatat fugiat fugiat magna consectetur id est mollit. Sit enim duis mollit dolor tempor cillum nisi aliquip elit consequat id ad.\r\n",
      "registered": "2016-05-31T05:08:19 -02:00",
      "latitude": -57.960062,
      "longitude": -160.3978,
      "tags": [
        "tempor",
        "exercitation",
        "est",
        "velit",
        "est",
        "in",
        "Lorem"
      ],
      "friends": [
        {
          "id": 0,
          "name": "Bianca Flowers"
        },
        {
          "id": 1,
          "name": "Essie Mason"
        },
        {
          "id": 2,
          "name": "Fran Sims"
        }
      ],
      "greeting": "Hello, Jenna Jacobson! You have 10 unread messages.",
      "favoriteFruit": "strawberry"
    },
    {
      "id": "6304f98b4aadf15a717e914a",
      "index": 18,
      "guid": "874a9789-9962-4533-9015-bd4b1d485cf2",
      "isActive": false,
      "balance": "$3,786.16",
      "picture": "http://placehold.it/32x32",
      "age": 25,
      "eyeColor": "blue",
      "name": "Nola Chaney",
      "gender": "female",
      "company": "DATAGENE",
      "email": "nolachaney@datagene.com",
      "phone": "+1 (950) 445-3864",
      "address": "286 Bainbridge Street, Dalton, Montana, 8137",
      "about": "Adipisicing deserunt consequat sit proident ex Lorem esse commodo amet culpa. Amet laboris velit anim dolor pariatur aliqua deserunt laboris. Occaecat amet nostrud id est qui nisi.\r\n",
      "registered": "2017-05-19T10:44:12 -02:00",
      "latitude": -29.821667,
      "longitude": -61.815932,
      "tags": [
        "velit",
        "minim",
        "exercitation",
        "reprehenderit",
        "labore",
        "aliqua",
        "nisi"
      ],
      "friends": [
        {
          "id": 0,
          "name": "Sparks Holloway"
        },
        {
          "id": 1,
          "name": "Janice Clayton"
        },
        {
          "id": 2,
          "name": "Oliver Winters"
        }
      ],
      "greeting": "Hello, Nola Chaney! You have 4 unread messages.",
      "favoriteFruit": "apple"
    },
    {
      "id": "6304f98b2ffb45c84d2b773f",
      "index": 19,
      "guid": "58c50186-fd69-4bae-8b68-eb4804466ec8",
      "isActive": true,
      "balance": "$1,373.99",
      "picture": "http://placehold.it/32x32",
      "age": 37,
      "eyeColor": "green",
      "name": "Clayton Hull",
      "gender": "male",
      "company": "SONGBIRD",
      "email": "claytonhull@songbird.com",
      "phone": "+1 (880) 500-3036",
      "address": "316 Hamilton Walk, Sisquoc, Michigan, 2312",
      "about": "Do nulla fugiat exercitation labore cupidatat elit laboris dolor ipsum do fugiat aute irure. Laboris ipsum laboris commodo reprehenderit consectetur laboris quis eu. Do nisi cillum elit dolor id dolor deserunt do excepteur ea laboris. Veniam sint occaecat pariatur qui. Ad ad fugiat esse quis tempor quis duis non officia.\r\n",
      "registered": "2018-10-28T02:27:59 -01:00",
      "latitude": 70.405598,
      "longitude": -157.917036,
      "tags": [
        "anim",
        "enim",
        "eiusmod",
        "velit",
        "in",
        "sunt",
        "velit"
      ],
      "friends": [
        {
          "id": 0,
          "name": "Dina Welch"
        },
        {
          "id": 1,
          "name": "Leon Tillman"
        },
        {
          "id": 2,
          "name": "Randolph Macias"
        }
      ],
      "greeting": "Hello, Clayton Hull! You have 4 unread messages.",
      "favoriteFruit": "apple"
    },
    {
      "id": "6304f98bd507f3dc12f7aab5",
      "index": 20,
      "guid": "4c0726b7-022c-41e2-8e36-674d547b2ea7",
      "isActive": false,
      "balance": "$2,345.77",
      "picture": "http://placehold.it/32x32",
      "age": 36,
      "eyeColor": "green",
      "name": "Golden Sherman",
      "gender": "male",
      "company": "FANFARE",
      "email": "goldensherman@fanfare.com",
      "phone": "+1 (859) 404-3647",
      "address": "919 Coleridge Street, Eureka, South Carolina, 7003",
      "about": "Dolor ipsum velit labore excepteur laborum nostrud occaecat proident qui sunt dolor labore. Nisi Lorem ipsum consequat consequat occaecat consectetur ullamco ad reprehenderit aliquip incididunt commodo nostrud cupidatat. Reprehenderit eu qui eiusmod culpa. Dolor elit aliquip enim cillum sit est sunt elit aute. Anim irure nulla sunt est est laboris.\r\n",
      "registered": "2016-07-19T03:55:54 -02:00",
      "latitude": 71.309793,
      "longitude": -81.358357,
      "tags": [
        "enim",
        "laborum",
        "tempor",
        "pariatur",
        "aute",
        "excepteur",
        "ut"
      ],
      "friends": [
        {
          "id": 0,
          "name": "Mallory Langley"
        },
        {
          "id": 1,
          "name": "Toni Farrell"
        },
        {
          "id": 2,
          "name": "Ericka Cooley"
        }
      ],
      "greeting": "Hello, Golden Sherman! You have 6 unread messages.",
      "favoriteFruit": "banana"
    },
    {
      "id": "6304f98ba7ca2c9a652ee40d",
      "index": 21,
      "guid": "19e51bc4-396a-4121-a626-424dd05c3878",
      "isActive": true,
      "balance": "$2,137.55",
      "picture": "http://placehold.it/32x32",
      "age": 22,
      "eyeColor": "blue",
      "name": "Brittany Powers",
      "gender": "female",
      "company": "UNQ",
      "email": "brittanypowers@unq.com",
      "phone": "+1 (854) 501-3412",
      "address": "817 Raleigh Place, Hondah, Massachusetts, 9289",
      "about": "Incididunt in mollit sint quis cillum officia excepteur magna exercitation aliquip aute tempor culpa. Incididunt aliquip sit in ea sit irure voluptate tempor in nisi occaecat enim. Enim occaecat et occaecat nisi qui dolore non ipsum incididunt.\r\n",
      "registered": "2021-10-08T01:16:23 -02:00",
      "latitude": 82.686122,
      "longitude": -149.976425,
      "tags": [
        "ex",
        "adipisicing",
        "excepteur",
        "eiusmod",
        "ad",
        "cillum",
        "irure"
      ],
      "friends": [
        {
          "id": 0,
          "name": "Chang Morgan"
        },
        {
          "id": 1,
          "name": "Enid Huffman"
        },
        {
          "id": 2,
          "name": "Ortiz Long"
        }
      ],
      "greeting": "Hello, Brittany Powers! You have 2 unread messages.",
      "favoriteFruit": "banana"
    },
    {
      "id": "6304f98b5c9758bfc4cb624a",
      "index": 22,
      "guid": "ffeb7095-9401-46d2-a5e9-18d838ce9986",
      "isActive": true,
      "balance": "$3,744.49",
      "picture": "http://placehold.it/32x32",
      "age": 26,
      "eyeColor": "green",
      "name": "Marva Snow",
      "gender": "female",
      "company": "TURNLING",
      "email": "marvasnow@turnling.com",
      "phone": "+1 (896) 562-3429",
      "address": "402 Himrod Street, Libertytown, New Jersey, 8468",
      "about": "Officia ex officia in labore mollit. Consectetur minim consectetur velit ut. Exercitation nisi ipsum magna ad et deserunt deserunt officia ipsum pariatur anim nisi aliquip. Mollit voluptate commodo anim nisi Lorem. Sunt laboris velit do dolore ex ex. Fugiat adipisicing cupidatat ea officia nulla minim aliquip consequat ad do.\r\n",
      "registered": "2016-07-21T08:11:28 -02:00",
      "latitude": -40.063681,
      "longitude": 49.006091,
      "tags": [
        "labore",
        "est",
        "consectetur",
        "anim",
        "officia",
        "nulla",
        "non"
      ],
      "friends": [
        {
          "id": 0,
          "name": "Dorsey Knight"
        },
        {
          "id": 1,
          "name": "Juarez Huber"
        },
        {
          "id": 2,
          "name": "Hartman Hawkins"
        }
      ],
      "greeting": "Hello, Marva Snow! You have 10 unread messages.",
      "favoriteFruit": "banana"
    },
    {
      "id": "6304f98ba1e30c55d33bc205",
      "index": 23,
      "guid": "9cea97da-c7bd-4412-b7a5-a90786a986f3",
      "isActive": true,
      "balance": "$2,515.52",
      "picture": "http://placehold.it/32x32",
      "age": 29,
      "eyeColor": "green",
      "name": "Aurelia Cruz",
      "gender": "female",
      "company": "MUSAPHICS",
      "email": "aureliacruz@musaphics.com",
      "phone": "+1 (951) 594-3340",
      "address": "223 Dewitt Avenue, Whitewater, Illinois, 4452",
      "about": "Ipsum sint consectetur duis nostrud est nostrud consectetur anim quis dolor ullamco ea. Sit ex ut pariatur magna pariatur nisi irure in velit. Velit fugiat tempor reprehenderit occaecat dolore do incididunt aliqua esse. Elit anim pariatur ut nisi consequat.\r\n",
      "registered": "2016-06-07T05:30:49 -02:00",
      "latitude": -85.347862,
      "longitude": -115.305533,
      "tags": [
        "occaecat",
        "nisi",
        "incididunt",
        "esse",
        "adipisicing",
        "amet",
        "ut"
      ],
      "friends": [
        {
          "id": 0,
          "name": "Jami Wolfe"
        },
        {
          "id": 1,
          "name": "Langley Yates"
        },
        {
          "id": 2,
          "name": "Cannon Beard"
        }
      ],
      "greeting": "Hello, Aurelia Cruz! You have 6 unread messages.",
      "favoriteFruit": "apple"
    },
    {
      "id": "6304f98b9b6bfb3b5d9ff9a9",
      "index": 24,
      "guid": "141afda4-694b-446b-b38a-79fa0aa50c63",
      "isActive": true,
      "balance": "$3,176.98",
      "picture": "http://placehold.it/32x32",
      "age": 21,
      "eyeColor": "brown",
      "name": "Mathews Leonard",
      "gender": "male",
      "company": "BLUPLANET",
      "email": "mathewsleonard@bluplanet.com",
      "phone": "+1 (917) 459-2332",
      "address": "809 Village Court, Carbonville, Virginia, 7637",
      "about": "Exercitation in voluptate quis sit adipisicing pariatur minim consequat pariatur et exercitation. Deserunt duis duis sint nostrud veniam velit ex adipisicing. Fugiat aute sint pariatur do duis enim ipsum qui enim non magna ullamco. Nulla amet anim consequat dolore aliquip in cillum quis est cillum est. Tempor non Lorem labore do magna excepteur id eiusmod duis do nostrud. Nisi mollit et ea quis commodo reprehenderit duis dolore officia.\r\n",
      "registered": "2015-07-05T11:37:16 -02:00",
      "latitude": 63.760426,
      "longitude": 142.273249,
      "tags": [
        "in",
        "est",
        "aute",
        "veniam",
        "nulla",
        "eu",
        "elit"
      ],
      "friends": [
        {
          "id": 0,
          "name": "Carlson Calhoun"
        },
        {
          "id": 1,
          "name": "Cochran Austin"
        },
        {
          "id": 2,
          "name": "Joan Hurst"
        }
      ],
      "greeting": "Hello, Mathews Leonard! You have 1 unread messages.",
      "favoriteFruit": "apple"
    },
    {
      "id": "6304f98bd28053477b4099ab",
      "index": 25,
      "guid": "f2fbcdb0-1b86-4994-84a7-dd1f262adf11",
      "isActive": true,
      "balance": "$2,149.40",
      "picture": "http://placehold.it/32x32",
      "age": 23,
      "eyeColor": "green",
      "name": "Dejesus Wise",
      "gender": "male",
      "company": "MAINELAND",
      "email": "dejesuswise@maineland.com",
      "phone": "+1 (992) 428-3301",
      "address": "847 Whitty Lane, Kenwood, Georgia, 5611",
      "about": "Culpa dolor Lorem in mollit dolor amet nostrud consectetur excepteur eu adipisicing. Et velit commodo ut excepteur reprehenderit consequat anim. Ex eiusmod ex labore aliquip id.\r\n",
      "registered": "2017-01-11T03:43:46 -01:00",
      "latitude": 35.413047,
      "longitude": 126.165456,
      "tags": [
        "voluptate",
        "amet",
        "officia",
        "sint",
        "id",
        "ut",
        "nisi"
      ],
      "friends": [
        {
          "id": 0,
          "name": "Mccullough Wolf"
        },
        {
          "id": 1,
          "name": "Kay Simpson"
        },
        {
          "id": 2,
          "name": "Lynnette Sawyer"
        }
      ],
      "greeting": "Hello, Dejesus Wise! You have 5 unread messages.",
      "favoriteFruit": "strawberry"
    },
    {
      "name": "Bogdan",
      "age": "35",
      "address": "Lacurilor 23",
      "id": "_ChAfG8"
    }
  ],
  "clients": [
    {
      "id": "6304fa577432cfcccb759ddd",
      "index": 0,
      "guid": "0e42302a-c12a-41b8-8520-b1846af771de",
      "isActive": true,
      "balance": "$2,261.60",
      "picture": "http://placehold.it/32x32",
      "age": 36,
      "eyeColor": "brown",
      "name": "Trina Price",
      "gender": "female",
      "company": "EXOPLODE",
      "email": "trinaprice@exoplode.com",
      "phone": "+1 (907) 401-2945",
      "address": "790 Cleveland Street, Dexter, Puerto Rico, 1909",
      "about": "Quis eu minim Lorem nulla minim qui esse ullamco voluptate in Lorem minim. Lorem eiusmod anim commodo excepteur. Pariatur mollit deserunt ea excepteur quis cillum eiusmod fugiat consectetur velit laborum ea. Consectetur laborum Lorem esse esse eu aliqua do do qui occaecat adipisicing nostrud. Enim excepteur nulla amet in. Sint fugiat sunt Lorem nulla id.\r\n",
      "registered": "2018-05-20T08:25:09 -02:00",
      "latitude": -54.098938,
      "longitude": 85.551269,
      "tags": [
        "non",
        "do",
        "laborum",
        "ipsum",
        "ad",
        "cupidatat",
        "qui"
      ],
      "friends": [
        {
          "id": 0,
          "name": "Gonzalez Jacobs"
        },
        {
          "id": 1,
          "name": "Camacho Mays"
        },
        {
          "id": 2,
          "name": "Boone Yang"
        }
      ],
      "greeting": "Hello, Trina Price! You have 10 unread messages.",
      "favoriteFruit": "strawberry"
    },
    {
      "id": "6304fa5737667add027c4e33",
      "index": 1,
      "guid": "7a4720a2-6cab-4dbf-a234-a2b7e2bafcc8",
      "isActive": false,
      "balance": "$2,011.71",
      "picture": "http://placehold.it/32x32",
      "age": 36,
      "eyeColor": "blue",
      "name": "Corina Peck",
      "gender": "female",
      "company": "ADORNICA",
      "email": "corinapeck@adornica.com",
      "phone": "+1 (801) 476-2312",
      "address": "731 Fuller Place, Takilma, Florida, 8039",
      "about": "Nulla proident nostrud laborum incididunt. Consequat duis sit et exercitation sunt. Voluptate reprehenderit esse minim commodo eu incididunt ad. Minim do exercitation ad sunt. Id deserunt irure enim nisi nulla aliquip consectetur qui ullamco duis.\r\n",
      "registered": "2015-08-28T12:32:14 -02:00",
      "latitude": 60.193033,
      "longitude": -171.301581,
      "tags": [
        "labore",
        "anim",
        "qui",
        "sunt",
        "eu",
        "ex",
        "ad"
      ],
      "friends": [
        {
          "id": 0,
          "name": "Beard Dejesus"
        },
        {
          "id": 1,
          "name": "Yvette Hughes"
        },
        {
          "id": 2,
          "name": "Hartman Cantu"
        }
      ],
      "greeting": "Hello, Corina Peck! You have 7 unread messages.",
      "favoriteFruit": "apple"
    },
    {
      "id": "6304fa57637dc2184c23bc3a",
      "index": 2,
      "guid": "087ddba7-24bd-4f22-907c-ca6f5f2106eb",
      "isActive": true,
      "balance": "$3,587.47",
      "picture": "http://placehold.it/32x32",
      "age": 39,
      "eyeColor": "brown",
      "name": "Davenport Wilder",
      "gender": "male",
      "company": "GEOSTELE",
      "email": "davenportwilder@geostele.com",
      "phone": "+1 (997) 421-3414",
      "address": "809 Amherst Street, Trexlertown, Guam, 2471",
      "about": "Laboris dolor non consectetur laborum Lorem Lorem ipsum consectetur fugiat velit. Est irure consequat Lorem pariatur est Lorem fugiat veniam. Voluptate qui sunt labore commodo fugiat consequat cupidatat laboris. Proident ut reprehenderit eiusmod nulla irure non ut ad ad mollit aliqua sit elit commodo. Enim sunt adipisicing anim elit. Exercitation magna ex aliqua laborum pariatur esse qui incididunt.\r\n",
      "registered": "2021-05-18T11:04:49 -02:00",
      "latitude": -15.707248,
      "longitude": -128.410153,
      "tags": [
        "et",
        "aliquip",
        "sint",
        "exercitation",
        "sint",
        "aute",
        "quis"
      ],
      "friends": [
        {
          "id": 0,
          "name": "Hopkins Hines"
        },
        {
          "id": 1,
          "name": "Tran Estrada"
        },
        {
          "id": 2,
          "name": "Trisha Brewer"
        }
      ],
      "greeting": "Hello, Davenport Wilder! You have 8 unread messages.",
      "favoriteFruit": "apple"
    },
    {
      "id": "6304fa578b46ae685c44a6ec",
      "index": 3,
      "guid": "949c388a-1a4b-472b-b073-960425a1c16c",
      "isActive": true,
      "balance": "$1,530.00",
      "picture": "http://placehold.it/32x32",
      "age": 26,
      "eyeColor": "green",
      "name": "Murray Ferguson",
      "gender": "male",
      "company": "ZANYMAX",
      "email": "murrayferguson@zanymax.com",
      "phone": "+1 (998) 526-2216",
      "address": "939 Dean Street, Websterville, Tennessee, 9769",
      "about": "Qui enim veniam sint sit Lorem nisi ex. Ea Lorem enim est non dolor. Aliquip quis adipisicing irure anim in ut cupidatat. Est laborum deserunt dolor adipisicing occaecat qui occaecat.\r\n",
      "registered": "2019-11-11T06:59:26 -01:00",
      "latitude": -0.807036,
      "longitude": -88.566561,
      "tags": [
        "duis",
        "consectetur",
        "anim",
        "ut",
        "ipsum",
        "elit",
        "consectetur"
      ],
      "friends": [
        {
          "id": 0,
          "name": "Mendez Larson"
        },
        {
          "id": 1,
          "name": "Simon Aguirre"
        },
        {
          "id": 2,
          "name": "Polly Roman"
        }
      ],
      "greeting": "Hello, Murray Ferguson! You have 3 unread messages.",
      "favoriteFruit": "apple"
    },
    {
      "id": "6304fa57f01bb5856503bb43",
      "index": 4,
      "guid": "2ccbf34e-410f-4acf-8c42-80c573c60c01",
      "isActive": true,
      "balance": "$2,528.12",
      "picture": "http://placehold.it/32x32",
      "age": 37,
      "eyeColor": "blue",
      "name": "Tucker House",
      "gender": "male",
      "company": "ZINCA",
      "email": "tuckerhouse@zinca.com",
      "phone": "+1 (974) 449-2376",
      "address": "966 Dorchester Road, Edinburg, Alabama, 7608",
      "about": "Nisi consectetur ad dolor aute laboris. Excepteur dolor occaecat ea cupidatat proident officia cillum ipsum pariatur consectetur cupidatat. Incididunt mollit sunt elit deserunt do. Commodo reprehenderit laborum consequat aliquip ad et commodo ad veniam quis et do aliqua.\r\n",
      "registered": "2017-10-25T08:25:47 -02:00",
      "latitude": 13.794406,
      "longitude": 26.424455,
      "tags": [
        "nisi",
        "eu",
        "laborum",
        "officia",
        "eu",
        "velit",
        "amet"
      ],
      "friends": [
        {
          "id": 0,
          "name": "Angel Schneider"
        },
        {
          "id": 1,
          "name": "Miranda Marks"
        },
        {
          "id": 2,
          "name": "Kitty Ashley"
        }
      ],
      "greeting": "Hello, Tucker House! You have 1 unread messages.",
      "favoriteFruit": "strawberry"
    },
    {
      "id": "6304fa57b17b450a5203e5a1",
      "index": 5,
      "guid": "0e10fb35-5a67-41b3-831c-c7bff5186ec2",
      "isActive": true,
      "balance": "$2,350.00",
      "picture": "http://placehold.it/32x32",
      "age": 27,
      "eyeColor": "green",
      "name": "Christensen Weber",
      "gender": "male",
      "company": "ROUGHIES",
      "email": "christensenweber@roughies.com",
      "phone": "+1 (858) 517-3909",
      "address": "737 Williams Court, Verdi, Oregon, 9372",
      "about": "Occaecat consequat dolore sint incididunt ad. Proident esse laboris fugiat duis ipsum cillum labore elit. Est Lorem magna Lorem cillum cupidatat aliquip ullamco ipsum qui. Consectetur eu fugiat id incididunt adipisicing. Cupidatat consectetur sint eiusmod reprehenderit et aliquip aliquip ex id aute enim incididunt.\r\n",
      "registered": "2015-11-01T05:20:51 -01:00",
      "latitude": 89.632695,
      "longitude": -174.496847,
      "tags": [
        "est",
        "qui",
        "ad",
        "culpa",
        "enim",
        "minim",
        "cupidatat"
      ],
      "friends": [
        {
          "id": 0,
          "name": "England Ford"
        },
        {
          "id": 1,
          "name": "Callahan Hood"
        },
        {
          "id": 2,
          "name": "Dodson Holder"
        }
      ],
      "greeting": "Hello, Christensen Weber! You have 3 unread messages.",
      "favoriteFruit": "apple"
    },
    {
      "id": "6304fa57d4bcd5e26d0b26fe",
      "index": 6,
      "guid": "58e34d21-7375-4a61-9664-cfa50f2aab5d",
      "isActive": true,
      "balance": "$2,499.99",
      "picture": "http://placehold.it/32x32",
      "age": 26,
      "eyeColor": "brown",
      "name": "Lorraine Garza",
      "gender": "female",
      "company": "BITREX",
      "email": "lorrainegarza@bitrex.com",
      "phone": "+1 (990) 418-3194",
      "address": "850 Clermont Avenue, Salvo, New York, 6234",
      "about": "Consequat aliquip proident tempor exercitation eu fugiat minim proident amet. Tempor irure aute ad proident esse consectetur id excepteur in nulla. Cillum sit veniam do minim est excepteur do cillum occaecat et qui ut fugiat. Mollit eiusmod velit ut esse ullamco proident adipisicing minim nisi.\r\n",
      "registered": "2014-06-18T04:15:37 -02:00",
      "latitude": 53.690667,
      "longitude": -135.252864,
      "tags": [
        "velit",
        "irure",
        "culpa",
        "incididunt",
        "aliquip",
        "fugiat",
        "proident"
      ],
      "friends": [
        {
          "id": 0,
          "name": "Waters Mooney"
        },
        {
          "id": 1,
          "name": "Hilda Fitzgerald"
        },
        {
          "id": 2,
          "name": "Lynn Herrera"
        }
      ],
      "greeting": "Hello, Lorraine Garza! You have 6 unread messages.",
      "favoriteFruit": "strawberry"
    },
    {
      "id": "6304fa57941e71824ef32eb2",
      "index": 7,
      "guid": "63c2ed34-5eaf-4447-97e8-d24b1ef9dedc",
      "isActive": true,
      "balance": "$1,933.78",
      "picture": "http://placehold.it/32x32",
      "age": 27,
      "eyeColor": "blue",
      "name": "Diann Harmon",
      "gender": "female",
      "company": "ZIDANT",
      "email": "diannharmon@zidant.com",
      "phone": "+1 (862) 451-2120",
      "address": "560 Greenpoint Avenue, Loyalhanna, Utah, 4357",
      "about": "Aute minim veniam ex quis aute ad aliquip aute dolor do. Enim proident dolore dolore elit quis non nulla elit in. Aliquip qui aliqua reprehenderit consectetur laborum labore do velit cupidatat et laboris labore nostrud qui. Ullamco exercitation anim ex sunt incididunt ex. Cillum adipisicing id deserunt ipsum consectetur ad excepteur ad dolore minim veniam pariatur.\r\n",
      "registered": "2016-03-05T12:25:53 -01:00",
      "latitude": 55.899088,
      "longitude": -145.556378,
      "tags": [
        "eu",
        "ipsum",
        "officia",
        "ipsum",
        "nisi",
        "ea",
        "deserunt"
      ],
      "friends": [
        {
          "id": 0,
          "name": "Harvey Stanley"
        },
        {
          "id": 1,
          "name": "Candy Ellis"
        },
        {
          "id": 2,
          "name": "Elvira Kirkland"
        }
      ],
      "greeting": "Hello, Diann Harmon! You have 5 unread messages.",
      "favoriteFruit": "apple"
    },
    {
      "id": "6304fa57c4b86d416639bdcf",
      "index": 8,
      "guid": "cb1ab502-8c25-40ac-bb35-85ae767e665c",
      "isActive": true,
      "balance": "$2,649.40",
      "picture": "http://placehold.it/32x32",
      "age": 23,
      "eyeColor": "brown",
      "name": "Walters William",
      "gender": "male",
      "company": "TURNABOUT",
      "email": "walterswilliam@turnabout.com",
      "phone": "+1 (891) 484-2405",
      "address": "478 Bennet Court, Thomasville, Washington, 3003",
      "about": "Qui magna cupidatat nulla ex excepteur nulla exercitation esse deserunt deserunt commodo velit veniam. Nostrud aliquip consectetur cupidatat eu cupidatat commodo non aliquip eu veniam. Irure duis nostrud exercitation labore sit exercitation deserunt reprehenderit commodo voluptate ea enim. Irure excepteur sint tempor dolor commodo nostrud velit reprehenderit nulla. Exercitation ipsum ipsum reprehenderit eu irure.\r\n",
      "registered": "2016-02-04T07:50:15 -01:00",
      "latitude": 4.345183,
      "longitude": 108.71317,
      "tags": [
        "commodo",
        "dolor",
        "amet",
        "culpa",
        "cillum",
        "elit",
        "qui"
      ],
      "friends": [
        {
          "id": 0,
          "name": "Harris Robertson"
        },
        {
          "id": 1,
          "name": "Elaine Duran"
        },
        {
          "id": 2,
          "name": "Janell Rivers"
        }
      ],
      "greeting": "Hello, Walters William! You have 10 unread messages.",
      "favoriteFruit": "apple"
    },
    {
      "id": "6304fa575925e311628338f2",
      "index": 9,
      "guid": "ff6cf238-8fdc-463f-98cc-9eec29dcb4db",
      "isActive": true,
      "balance": "$2,027.78",
      "picture": "http://placehold.it/32x32",
      "age": 20,
      "eyeColor": "blue",
      "name": "Browning Bush",
      "gender": "male",
      "company": "IDEGO",
      "email": "browningbush@idego.com",
      "phone": "+1 (933) 445-3881",
      "address": "522 Jay Street, Crenshaw, Virginia, 3864",
      "about": "Aliquip est occaecat tempor occaecat eu laborum occaecat nulla excepteur non nostrud sunt. Lorem commodo aute tempor in excepteur mollit cillum proident deserunt do ullamco excepteur. Duis tempor irure officia occaecat et cillum tempor dolore sit commodo.\r\n",
      "registered": "2014-03-28T12:25:49 -01:00",
      "latitude": 26.283449,
      "longitude": -1.800434,
      "tags": [
        "exercitation",
        "officia",
        "ex",
        "proident",
        "ut",
        "culpa",
        "ad"
      ],
      "friends": [
        {
          "id": 0,
          "name": "Downs Moses"
        },
        {
          "id": 1,
          "name": "Winifred Atkinson"
        },
        {
          "id": 2,
          "name": "Norma Richardson"
        }
      ],
      "greeting": "Hello, Browning Bush! You have 10 unread messages.",
      "favoriteFruit": "strawberry"
    },
    {
      "id": "6304fa579bd36e06f09d8daf",
      "index": 10,
      "guid": "9b2df55b-86f0-44f1-bd40-d3b68369a64a",
      "isActive": false,
      "balance": "$1,439.11",
      "picture": "http://placehold.it/32x32",
      "age": 36,
      "eyeColor": "brown",
      "name": "Mooney Humphrey",
      "gender": "male",
      "company": "REVERSUS",
      "email": "mooneyhumphrey@reversus.com",
      "phone": "+1 (864) 451-2296",
      "address": "270 Kossuth Place, Leola, Minnesota, 405",
      "about": "Eu velit pariatur commodo esse duis sunt anim est reprehenderit ullamco officia. Est ea exercitation non magna consectetur minim quis occaecat nulla ea velit aute. Nulla aute excepteur tempor proident nisi laboris labore dolore. Laboris sit aliqua tempor exercitation ut laboris tempor dolore magna aute qui velit cupidatat. Officia ipsum Lorem adipisicing nostrud veniam veniam ullamco commodo. Consectetur laborum veniam aliquip exercitation. Labore sint proident minim nisi.\r\n",
      "registered": "2018-03-18T07:41:04 -01:00",
      "latitude": -4.011048,
      "longitude": 21.491212,
      "tags": [
        "fugiat",
        "do",
        "adipisicing",
        "nulla",
        "nisi",
        "est",
        "commodo"
      ],
      "friends": [
        {
          "id": 0,
          "name": "Terry Orr"
        },
        {
          "id": 1,
          "name": "Louella Houston"
        },
        {
          "id": 2,
          "name": "Kellie Delacruz"
        }
      ],
      "greeting": "Hello, Mooney Humphrey! You have 1 unread messages.",
      "favoriteFruit": "apple"
    },
    {
      "id": "6304fa57bbc92476ca11b328",
      "index": 11,
      "guid": "df2aea74-aa8d-4850-89b3-b7246cfe39b7",
      "isActive": true,
      "balance": "$3,421.64",
      "picture": "http://placehold.it/32x32",
      "age": 37,
      "eyeColor": "brown",
      "name": "Calderon Baxter",
      "gender": "male",
      "company": "ENTALITY",
      "email": "calderonbaxter@entality.com",
      "phone": "+1 (926) 406-2520",
      "address": "170 Bowne Street, Wikieup, Alaska, 3310",
      "about": "Pariatur nostrud Lorem id dolor magna velit esse elit cupidatat. Anim enim fugiat duis reprehenderit cupidatat tempor incididunt qui non dolore. Minim sit fugiat laborum quis reprehenderit aute eiusmod in. Ad fugiat laborum Lorem eiusmod labore incididunt ex dolor deserunt esse id labore tempor deserunt.\r\n",
      "registered": "2017-04-08T10:35:03 -02:00",
      "latitude": -23.887045,
      "longitude": 134.427676,
      "tags": [
        "qui",
        "irure",
        "excepteur",
        "ipsum",
        "elit",
        "excepteur",
        "duis"
      ],
      "friends": [
        {
          "id": 0,
          "name": "Nieves Moreno"
        },
        {
          "id": 1,
          "name": "Higgins Callahan"
        },
        {
          "id": 2,
          "name": "Carmen Powell"
        }
      ],
      "greeting": "Hello, Calderon Baxter! You have 1 unread messages.",
      "favoriteFruit": "strawberry"
    },
    {
      "id": "6304fa577e3e28ced7f64936",
      "index": 12,
      "guid": "4075f5fe-aec4-4e49-be5e-24fc6876b199",
      "isActive": false,
      "balance": "$2,548.59",
      "picture": "http://placehold.it/32x32",
      "age": 38,
      "eyeColor": "brown",
      "name": "Montoya Herman",
      "gender": "male",
      "company": "QUANTALIA",
      "email": "montoyaherman@quantalia.com",
      "phone": "+1 (835) 440-2436",
      "address": "151 Alice Court, Homestead, Wyoming, 8864",
      "about": "Lorem do commodo enim magna excepteur incididunt excepteur. Eu fugiat laborum culpa officia in ex reprehenderit adipisicing ad enim aliquip. Ea commodo nulla laboris labore occaecat reprehenderit do aute. Occaecat ex Lorem do dolor quis nostrud magna culpa irure quis eu. Adipisicing magna exercitation sint magna cupidatat sunt labore eiusmod tempor voluptate. Qui magna pariatur ut velit laborum eu sint eu adipisicing reprehenderit cupidatat occaecat proident exercitation. Occaecat dolore labore tempor eu Lorem anim irure velit ullamco duis.\r\n",
      "registered": "2015-05-30T04:43:48 -02:00",
      "latitude": 86.235544,
      "longitude": 145.268321,
      "tags": [
        "proident",
        "sit",
        "officia",
        "velit",
        "elit",
        "culpa",
        "enim"
      ],
      "friends": [
        {
          "id": 0,
          "name": "Carey Joseph"
        },
        {
          "id": 1,
          "name": "Tonya Morris"
        },
        {
          "id": 2,
          "name": "Laurie Reed"
        }
      ],
      "greeting": "Hello, Montoya Herman! You have 7 unread messages.",
      "favoriteFruit": "strawberry"
    },
    {
      "id": "6304fa5713a6e56c43389776",
      "index": 13,
      "guid": "ccaecf17-6526-43e6-96ae-02dddd825faf",
      "isActive": true,
      "balance": "$2,804.54",
      "picture": "http://placehold.it/32x32",
      "age": 34,
      "eyeColor": "green",
      "name": "Felicia Holcomb",
      "gender": "female",
      "company": "SQUISH",
      "email": "feliciaholcomb@squish.com",
      "phone": "+1 (968) 430-2287",
      "address": "771 Canda Avenue, Canterwood, Northern Mariana Islands, 9527",
      "about": "Anim duis fugiat nulla esse duis aute occaecat id adipisicing. Et aliqua exercitation quis non aliquip minim ea nisi excepteur. Voluptate ipsum nisi quis ad pariatur officia culpa quis magna. Pariatur eu ut mollit incididunt mollit incididunt do duis pariatur eiusmod ut. Ipsum nisi tempor ullamco ex labore amet occaecat dolor pariatur incididunt cillum est. Adipisicing pariatur esse sunt laborum id pariatur. Do quis et sint do ad labore excepteur ea.\r\n",
      "registered": "2015-02-18T11:58:59 -01:00",
      "latitude": 42.256139,
      "longitude": 138.58474,
      "tags": [
        "culpa",
        "deserunt",
        "cupidatat",
        "eiusmod",
        "voluptate",
        "fugiat",
        "proident"
      ],
      "friends": [
        {
          "id": 0,
          "name": "Loraine Le"
        },
        {
          "id": 1,
          "name": "Guthrie Patterson"
        },
        {
          "id": 2,
          "name": "Sonja Oconnor"
        }
      ],
      "greeting": "Hello, Felicia Holcomb! You have 9 unread messages.",
      "favoriteFruit": "banana"
    },
    {
      "id": "6304fa5758d178bacd31c6eb",
      "index": 14,
      "guid": "9fa2440e-4df1-4e75-855b-04fcf5c99188",
      "isActive": false,
      "balance": "$3,224.91",
      "picture": "http://placehold.it/32x32",
      "age": 34,
      "eyeColor": "green",
      "name": "Bobbie Battle",
      "gender": "female",
      "company": "SINGAVERA",
      "email": "bobbiebattle@singavera.com",
      "phone": "+1 (886) 410-2185",
      "address": "301 Estate Road, Alderpoint, Louisiana, 2307",
      "about": "Enim laboris laboris excepteur pariatur qui tempor eu. Est laborum enim veniam dolore. Et proident tempor laboris ea irure dolor enim adipisicing sint.\r\n",
      "registered": "2015-11-20T06:32:01 -01:00",
      "latitude": -29.685558,
      "longitude": -47.695632,
      "tags": [
        "in",
        "aliquip",
        "incididunt",
        "velit",
        "fugiat",
        "dolore",
        "esse"
      ],
      "friends": [
        {
          "id": 0,
          "name": "Levine Lewis"
        },
        {
          "id": 1,
          "name": "Decker Herring"
        },
        {
          "id": 2,
          "name": "Margaret Tucker"
        }
      ],
      "greeting": "Hello, Bobbie Battle! You have 1 unread messages.",
      "favoriteFruit": "apple"
    },
    {
      "id": "6304fa579409e9f927a6a0b5",
      "index": 15,
      "guid": "dfedcb82-c2d5-4cc4-a55f-aded15127aa1",
      "isActive": true,
      "balance": "$3,432.55",
      "picture": "http://placehold.it/32x32",
      "age": 37,
      "eyeColor": "brown",
      "name": "Bartlett Dickson",
      "gender": "male",
      "company": "EZENTIA",
      "email": "bartlettdickson@ezentia.com",
      "phone": "+1 (988) 499-2916",
      "address": "749 Portal Street, Waumandee, Maryland, 5138",
      "about": "Voluptate excepteur incididunt nisi adipisicing aliqua laborum. Veniam Lorem ullamco elit nisi ullamco. Ad anim irure irure aliqua ea cillum sunt voluptate laborum magna irure aliqua.\r\n",
      "registered": "2018-04-01T02:37:08 -02:00",
      "latitude": 85.487399,
      "longitude": -71.999727,
      "tags": [
        "est",
        "eiusmod",
        "deserunt",
        "esse",
        "ad",
        "consectetur",
        "aliqua"
      ],
      "friends": [
        {
          "id": 0,
          "name": "Doyle Mcintosh"
        },
        {
          "id": 1,
          "name": "Cobb Vaughn"
        },
        {
          "id": 2,
          "name": "Durham Melton"
        }
      ],
      "greeting": "Hello, Bartlett Dickson! You have 4 unread messages.",
      "favoriteFruit": "strawberry"
    },
    {
      "id": "6304fa573fad9e988ea02935",
      "index": 16,
      "guid": "44a36161-2651-4838-b772-812664139066",
      "isActive": true,
      "balance": "$1,448.82",
      "picture": "http://placehold.it/32x32",
      "age": 20,
      "eyeColor": "blue",
      "name": "Silva Villarreal",
      "gender": "male",
      "company": "MEDCOM",
      "email": "silvavillarreal@medcom.com",
      "phone": "+1 (803) 402-3500",
      "address": "291 Junius Street, Celeryville, Virgin Islands, 2259",
      "about": "Sit fugiat qui Lorem ullamco reprehenderit. Tempor anim ad exercitation deserunt exercitation officia est. Aute ad duis elit occaecat minim enim aliquip sunt amet. Labore elit laboris officia et laborum irure do sunt incididunt proident.\r\n",
      "registered": "2017-01-21T09:55:15 -01:00",
      "latitude": 40.175238,
      "longitude": 35.880438,
      "tags": [
        "quis",
        "deserunt",
        "consequat",
        "esse",
        "ex",
        "non",
        "laborum"
      ],
      "friends": [
        {
          "id": 0,
          "name": "Freida Allison"
        },
        {
          "id": 1,
          "name": "Greer Jenkins"
        },
        {
          "id": 2,
          "name": "Padilla Knox"
        }
      ],
      "greeting": "Hello, Silva Villarreal! You have 6 unread messages.",
      "favoriteFruit": "banana"
    },
    {
      "id": "6304fa573bd44e0f713c9bd4",
      "index": 17,
      "guid": "baaea902-bfbf-4d23-879f-f4bd51760c68",
      "isActive": false,
      "balance": "$3,875.02",
      "picture": "http://placehold.it/32x32",
      "age": 21,
      "eyeColor": "blue",
      "name": "Snider Mcdowell",
      "gender": "male",
      "company": "ENDIPINE",
      "email": "snidermcdowell@endipine.com",
      "phone": "+1 (977) 488-2825",
      "address": "245 Falmouth Street, Magnolia, Nebraska, 1564",
      "about": "Consequat mollit ea aliqua cupidatat pariatur nostrud cillum ad amet consectetur. Qui officia velit commodo velit sunt id. Fugiat velit consectetur laborum irure qui sint eu voluptate cillum eiusmod aute. Deserunt ad reprehenderit adipisicing consectetur eiusmod incididunt id sunt voluptate est mollit pariatur cillum. Labore sit ut dolor est irure ullamco pariatur eiusmod est quis quis voluptate incididunt. Ut culpa est veniam dolor sunt qui esse velit nulla anim do.\r\n",
      "registered": "2018-03-22T08:48:36 -01:00",
      "latitude": 51.414397,
      "longitude": -128.203259,
      "tags": [
        "labore",
        "ex",
        "magna",
        "tempor",
        "amet",
        "commodo",
        "laboris"
      ],
      "friends": [
        {
          "id": 0,
          "name": "Ferguson Lancaster"
        },
        {
          "id": 1,
          "name": "Gale Stephenson"
        },
        {
          "id": 2,
          "name": "Potter Booker"
        }
      ],
      "greeting": "Hello, Snider Mcdowell! You have 5 unread messages.",
      "favoriteFruit": "strawberry"
    },
    {
      "id": "6304fa573a5a34eeb4bc5483",
      "index": 18,
      "guid": "74231530-1be1-4309-a052-f7151a7c4b10",
      "isActive": false,
      "balance": "$2,090.78",
      "picture": "http://placehold.it/32x32",
      "age": 37,
      "eyeColor": "green",
      "name": "Rosalie Vasquez",
      "gender": "female",
      "company": "ZAYA",
      "email": "rosalievasquez@zaya.com",
      "phone": "+1 (983) 578-2515",
      "address": "946 Fillmore Place, Rivereno, New Jersey, 8257",
      "about": "Laboris anim occaecat excepteur nulla veniam ullamco voluptate. Sit dolore sit dolore Lorem cupidatat anim occaecat. Eiusmod irure anim excepteur mollit adipisicing pariatur. Irure Lorem nostrud culpa sunt. Occaecat fugiat aliqua irure ut nulla in ad. Consectetur non do veniam magna quis sint id veniam ea quis occaecat excepteur sint.\r\n",
      "registered": "2021-02-23T08:46:01 -01:00",
      "latitude": -73.281104,
      "longitude": 128.137284,
      "tags": [
        "est",
        "tempor",
        "dolore",
        "mollit",
        "reprehenderit",
        "enim",
        "dolor"
      ],
      "friends": [
        {
          "id": 0,
          "name": "Darcy Leonard"
        },
        {
          "id": 1,
          "name": "Dorsey Nash"
        },
        {
          "id": 2,
          "name": "Angeline Morton"
        }
      ],
      "greeting": "Hello, Rosalie Vasquez! You have 8 unread messages.",
      "favoriteFruit": "strawberry"
    },
    {
      "id": "6304fa57be493a4a86756e4d",
      "index": 19,
      "guid": "e591a0ca-63fd-4af3-b716-ab8169bac8ae",
      "isActive": true,
      "balance": "$1,535.00",
      "picture": "http://placehold.it/32x32",
      "age": 26,
      "eyeColor": "blue",
      "name": "Gay Booth",
      "gender": "female",
      "company": "ZOLAVO",
      "email": "gaybooth@zolavo.com",
      "phone": "+1 (961) 597-2053",
      "address": "264 Himrod Street, Sanborn, Idaho, 6296",
      "about": "Labore ex fugiat ut velit. Officia pariatur ut nostrud non adipisicing sint ullamco. Lorem incididunt nulla amet consectetur nostrud adipisicing Lorem laboris non laboris ad. Proident cupidatat fugiat reprehenderit cupidatat. Qui esse magna aliqua duis deserunt anim commodo.\r\n",
      "registered": "2016-11-19T10:27:39 -01:00",
      "latitude": 71.670247,
      "longitude": 24.077616,
      "tags": [
        "esse",
        "exercitation",
        "id",
        "irure",
        "id",
        "deserunt",
        "dolore"
      ],
      "friends": [
        {
          "id": 0,
          "name": "Alicia Craft"
        },
        {
          "id": 1,
          "name": "Ursula Frederick"
        },
        {
          "id": 2,
          "name": "William Lyons"
        }
      ],
      "greeting": "Hello, Gay Booth! You have 4 unread messages.",
      "favoriteFruit": "apple"
    },
    {
      "id": "6304fa5727fb13de33741159",
      "index": 20,
      "guid": "e1785121-5cf2-43c4-8370-b83a6d41befd",
      "isActive": false,
      "balance": "$3,976.62",
      "picture": "http://placehold.it/32x32",
      "age": 35,
      "eyeColor": "green",
      "name": "Byers White",
      "gender": "male",
      "company": "ACUSAGE",
      "email": "byerswhite@acusage.com",
      "phone": "+1 (931) 526-2863",
      "address": "614 Hegeman Avenue, Camino, Kentucky, 7946",
      "about": "Anim culpa eiusmod sit nostrud ipsum adipisicing Lorem et qui. Id quis veniam sit ad adipisicing pariatur adipisicing dolore laborum anim. Commodo mollit excepteur nisi nisi ut minim duis proident laboris duis do. Esse culpa fugiat Lorem reprehenderit nisi ea non ipsum sunt dolor. Commodo minim sint sint consectetur elit qui. Velit ad eiusmod fugiat duis. Exercitation ipsum eiusmod incididunt in nulla id exercitation cillum.\r\n",
      "registered": "2021-06-04T08:23:47 -02:00",
      "latitude": 74.500183,
      "longitude": 8.389122,
      "tags": [
        "dolore",
        "deserunt",
        "deserunt",
        "laborum",
        "velit",
        "fugiat",
        "magna"
      ],
      "friends": [
        {
          "id": 0,
          "name": "Betty Delaney"
        },
        {
          "id": 1,
          "name": "Walter Slater"
        },
        {
          "id": 2,
          "name": "Patrica Moss"
        }
      ],
      "greeting": "Hello, Byers White! You have 7 unread messages.",
      "favoriteFruit": "banana"
    },
    {
      "id": "6304fa57b5f8e55be2410490",
      "index": 21,
      "guid": "8109ad76-288a-4c8c-a418-1c5027f3c328",
      "isActive": true,
      "balance": "$3,349.63",
      "picture": "http://placehold.it/32x32",
      "age": 32,
      "eyeColor": "brown",
      "name": "Bonner Jarvis",
      "gender": "male",
      "company": "ANIMALIA",
      "email": "bonnerjarvis@animalia.com",
      "phone": "+1 (850) 564-2651",
      "address": "841 Chestnut Street, Grazierville, Oklahoma, 216",
      "about": "Magna voluptate dolore laborum ad irure nisi incididunt quis in eiusmod excepteur sit eiusmod. Quis velit commodo mollit Lorem excepteur velit fugiat. Consequat laboris mollit consectetur ad.\r\n",
      "registered": "2015-02-06T08:04:09 -01:00",
      "latitude": 11.164656,
      "longitude": -29.682966,
      "tags": [
        "enim",
        "ex",
        "do",
        "Lorem",
        "nulla",
        "excepteur",
        "proident"
      ],
      "friends": [
        {
          "id": 0,
          "name": "Nunez Hyde"
        },
        {
          "id": 1,
          "name": "Regina Todd"
        },
        {
          "id": 2,
          "name": "Alyce Nieves"
        }
      ],
      "greeting": "Hello, Bonner Jarvis! You have 7 unread messages.",
      "favoriteFruit": "strawberry"
    },
    {
      "id": "6304fa578b701e127666b408",
      "index": 22,
      "guid": "430f7a92-5b65-42e9-9183-324188c273b7",
      "isActive": true,
      "balance": "$3,664.07",
      "picture": "http://placehold.it/32x32",
      "age": 27,
      "eyeColor": "blue",
      "name": "Benton Cole",
      "gender": "male",
      "company": "DOGNOST",
      "email": "bentoncole@dognost.com",
      "phone": "+1 (888) 573-3369",
      "address": "946 Wortman Avenue, Rockhill, South Dakota, 5424",
      "about": "Aliqua velit sint reprehenderit culpa laborum cupidatat ullamco cupidatat sit commodo eu. Reprehenderit aute irure consequat occaecat eiusmod laborum culpa incididunt nostrud enim aute duis sit. Est voluptate ut nostrud eiusmod elit magna Lorem dolore magna adipisicing eiusmod commodo anim sit. Eiusmod ad nisi voluptate id mollit aliquip do cupidatat qui amet est amet. Labore incididunt adipisicing pariatur dolore minim duis officia nostrud ex velit et irure. Nisi nulla occaecat esse ullamco voluptate culpa aliquip. Minim commodo dolor esse consequat sint pariatur fugiat minim.\r\n",
      "registered": "2017-02-03T12:07:31 -01:00",
      "latitude": -63.280911,
      "longitude": 113.281818,
      "tags": [
        "id",
        "enim",
        "esse",
        "fugiat",
        "non",
        "do",
        "veniam"
      ],
      "friends": [
        {
          "id": 0,
          "name": "Jannie Hawkins"
        },
        {
          "id": 1,
          "name": "Morrow Holt"
        },
        {
          "id": 2,
          "name": "Myrtle Britt"
        }
      ],
      "greeting": "Hello, Benton Cole! You have 7 unread messages.",
      "favoriteFruit": "strawberry"
    },
    {
      "id": "6304fa57affb83ee1fe7226a",
      "index": 23,
      "guid": "ef0107fd-dc56-47d7-b56f-d0f1d3d3d750",
      "isActive": true,
      "balance": "$2,735.64",
      "picture": "http://placehold.it/32x32",
      "age": 27,
      "eyeColor": "blue",
      "name": "Trujillo Gutierrez",
      "gender": "male",
      "company": "ZEPITOPE",
      "email": "trujillogutierrez@zepitope.com",
      "phone": "+1 (969) 428-3841",
      "address": "902 Mill Road, Iola, California, 7253",
      "about": "Nostrud magna eiusmod sint laborum. Irure nostrud cupidatat enim eu consequat elit eu deserunt. Laboris ullamco labore voluptate nisi sit culpa proident labore. Ad ea enim deserunt do ea enim enim consequat nulla dolor ad.\r\n",
      "registered": "2019-03-17T08:39:02 -01:00",
      "latitude": 42.63099,
      "longitude": 41.312144,
      "tags": [
        "cupidatat",
        "ad",
        "labore",
        "laborum",
        "deserunt",
        "ut",
        "minim"
      ],
      "friends": [
        {
          "id": 0,
          "name": "Hendrix Hartman"
        },
        {
          "id": 1,
          "name": "Medina Shannon"
        },
        {
          "id": 2,
          "name": "Luann Meadows"
        }
      ],
      "greeting": "Hello, Trujillo Gutierrez! You have 6 unread messages.",
      "favoriteFruit": "strawberry"
    },
    {
      "id": "6304fa57790f50339b30cc36",
      "index": 24,
      "guid": "e81f7806-dcaf-4b6c-a8f2-073d08538cc3",
      "isActive": true,
      "balance": "$3,225.48",
      "picture": "http://placehold.it/32x32",
      "age": 38,
      "eyeColor": "brown",
      "name": "Earlene Cooper",
      "gender": "female",
      "company": "XOGGLE",
      "email": "earlenecooper@xoggle.com",
      "phone": "+1 (877) 550-2397",
      "address": "400 Norwood Avenue, Rose, Connecticut, 6860",
      "about": "Laboris irure do Lorem ex adipisicing dolore est sint nulla veniam ea qui. Laborum ut reprehenderit duis occaecat. Magna pariatur in occaecat cupidatat. Reprehenderit aute mollit in esse irure qui velit.\r\n",
      "registered": "2019-05-23T07:31:11 -02:00",
      "latitude": -64.656403,
      "longitude": 65.597008,
      "tags": [
        "id",
        "aliquip",
        "consequat",
        "quis",
        "id",
        "nulla",
        "laboris"
      ],
      "friends": [
        {
          "id": 0,
          "name": "Pruitt Harding"
        },
        {
          "id": 1,
          "name": "Sweet Rush"
        },
        {
          "id": 2,
          "name": "Olson Harrell"
        }
      ],
      "greeting": "Hello, Earlene Cooper! You have 10 unread messages.",
      "favoriteFruit": "apple"
    },
    {
      "id": "6304fa57983951b4f51a50d3",
      "index": 25,
      "guid": "2fa4196c-7b3f-4649-81b0-cd5062b14544",
      "isActive": false,
      "balance": "$3,259.01",
      "picture": "http://placehold.it/32x32",
      "age": 38,
      "eyeColor": "brown",
      "name": "Sweeney Lindsay",
      "gender": "male",
      "company": "GENMOM",
      "email": "sweeneylindsay@genmom.com",
      "phone": "+1 (809) 423-2477",
      "address": "738 Elm Place, Muse, Palau, 4474",
      "about": "Do sit adipisicing occaecat aute nostrud velit laboris aliqua do minim elit ex culpa et. Est anim tempor et proident voluptate pariatur eiusmod esse ullamco sunt fugiat voluptate Lorem. Do sit ullamco in exercitation sunt fugiat aliquip. Tempor incididunt anim sint consectetur veniam nulla aliqua anim esse nostrud.\r\n",
      "registered": "2019-01-21T11:57:51 -01:00",
      "latitude": -18.168742,
      "longitude": 139.901329,
      "tags": [
        "ut",
        "excepteur",
        "anim",
        "reprehenderit",
        "incididunt",
        "ullamco",
        "in"
      ],
      "friends": [
        {
          "id": 0,
          "name": "Robert Velasquez"
        },
        {
          "id": 1,
          "name": "Moreno Thornton"
        },
        {
          "id": 2,
          "name": "Blair Mccormick"
        }
      ],
      "greeting": "Hello, Sweeney Lindsay! You have 4 unread messages.",
      "favoriteFruit": "apple"
    },
    {
      "id": "6304fa57574ba6d27a13b0a1",
      "index": 26,
      "guid": "9bce5b3c-33d7-4c9e-b50b-aa0a2961ca40",
      "isActive": false,
      "balance": "$2,567.50",
      "picture": "http://placehold.it/32x32",
      "age": 27,
      "eyeColor": "green",
      "name": "Rich Steele",
      "gender": "male",
      "company": "BICOL",
      "email": "richsteele@bicol.com",
      "phone": "+1 (912) 545-3178",
      "address": "766 Fountain Avenue, Lawrence, District Of Columbia, 3817",
      "about": "Ea elit quis occaecat culpa aliqua veniam pariatur officia officia minim enim eiusmod sit. Sunt occaecat deserunt mollit officia amet aliqua do Lorem proident fugiat in qui tempor. Laborum ea occaecat nisi labore magna Lorem occaecat dolor tempor ex magna consequat culpa in. Pariatur reprehenderit do consectetur veniam et. Lorem duis laborum voluptate labore fugiat proident ipsum elit qui consequat Lorem.\r\n",
      "registered": "2019-08-20T10:26:04 -02:00",
      "latitude": -8.040184,
      "longitude": -0.949602,
      "tags": [
        "sit",
        "proident",
        "laborum",
        "eiusmod",
        "quis",
        "adipisicing",
        "occaecat"
      ],
      "friends": [
        {
          "id": 0,
          "name": "Vinson Martin"
        },
        {
          "id": 1,
          "name": "Suzette Hernandez"
        },
        {
          "id": 2,
          "name": "Stevenson Short"
        }
      ],
      "greeting": "Hello, Rich Steele! You have 10 unread messages.",
      "favoriteFruit": "apple"
    }
  ]
}